itss/__init__.py
itss/fun1.py
itss/fun2.py
itss-0.3.dist-info/LICENCE.txt
itss-0.3.dist-info/METADATA
itss-0.3.dist-info/WHEEL
itss-0.3.dist-info/top_level.txt
itss-0.3.dist-info/RECORD
