Metadata-Version: 2.1
Name: itss
Version: 0.3
Summary: BASIC PACKAGE
Author: Nitghingowda A M
Author-email: nithingowdaam.itss@gmail.com
Classifier: Programming Language :: Python :: 2
Classifier: Programming Language :: Python :: 2.7
Classifier: License :: OSI Approved :: MIT License
Classifier: Operating System :: OS Independent
License-File: LICENCE.txt
